topk_bench-0.1.1.dist-info/METADATA
topk_bench-0.1.1.dist-info/WHEEL
topk_bench/__init__.py
topk_bench/providers/__init__.py
topk_bench/providers/milvus.py
topk_bench/providers/pinecone.py
topk_bench/providers/qdrant.py
topk_bench/providers/topk.py
topk_bench/providers/turbopuffer.py
topk_bench/topk_bench.cpython-311-arm-linux-gnueabihf.so
topk_bench/topk_bench.pyi
topk_bench-0.1.1.dist-info/RECORD
