Metadata-Version: 2.4
Name: topk_bench
Version: 0.1.1
Classifier: Programming Language :: Rust
Classifier: Programming Language :: Python :: Implementation :: CPython
Classifier: Programming Language :: Python :: Implementation :: PyPy
Requires-Dist: duckdb>=1.3.2
Requires-Dist: ipykernel>=6.0.0
Requires-Dist: jupyter>=1.0.0
Requires-Dist: maturin>=1.10.1
Requires-Dist: pinecone[grpc]>=5.4.2
Requires-Dist: pyarrow>=17.0.0
Requires-Dist: pymilvus<2.6
Requires-Dist: qdrant-client>=1.12.1
Requires-Dist: topk-sdk>=0.1.5
Requires-Dist: turbopuffer>=1.5.0
Requires-Dist: ty>=0.0.1a26
Requires-Dist: typer>=0.20.0
Summary: A reproducible benchmarking tool for evaluating vector databases under realistic workloads.
Requires-Python: >=3.8
